uecp/__init__.py
uecp/byte_stuffing_codec.py
uecp/commands/__init__.py
uecp/commands/base.py
uecp/commands/bidirectional.py
uecp/commands/clock_control.py
uecp/commands/control_n_setup.py
uecp/commands/mixins.py
uecp/commands/rds_control.py
uecp/commands/rds_message.py
uecp/frame.py
uecp/rds_character_set_codec.py
uecp/serial_con/__init__.py
uecp/serial_con/device.py
uecp/serial_con/protocol.py
uecp-0.4.0.dist-info/LICENSE
uecp-0.4.0.dist-info/METADATA
uecp-0.4.0.dist-info/WHEEL
uecp-0.4.0.dist-info/RECORD
