Metadata-Version: 2.1
Name: uecp
Version: 0.4.0
Summary: UECP encoder & decoder
License: MIT
Keywords: UECP,RDS,Radio,FM
Author: Christian Kohlstedde
Author-email: christian@kohlsted.de
Requires-Python: >=3.11,<4.0
Classifier: Development Status :: 2 - Pre-Alpha
Classifier: Intended Audience :: Developers
Classifier: License :: OSI Approved :: MIT License
Classifier: Natural Language :: English
Classifier: Natural Language :: German
Classifier: Programming Language :: Python :: 3
Classifier: Programming Language :: Python :: 3.11
Classifier: Programming Language :: Python :: 3.12
Requires-Dist: attrs (>=23.2.0,<24.0.0)
Requires-Dist: crc (>=1.2.0,<2.0.0)
Requires-Dist: pyserial (>=3.5,<4.0)
Requires-Dist: pyserial-asyncio (>=0.6,<0.7)
